LICENSE
MANIFEST.in
README.rst
setup.py
yahooweather.py
yahooweather.egg-info/PKG-INFO
yahooweather.egg-info/SOURCES.txt
yahooweather.egg-info/dependency_links.txt
yahooweather.egg-info/not-zip-safe
yahooweather.egg-info/top_level.txt