Metadata-Version: 1.1
Name: yahooweather
Version: 0.10
Summary: a Python module that provides an interface to the Yahoo! Weather RSS feed.
Home-page: https://github.com/pvizeli/yahooweather
Author: Pascal Vizeli
Author-email: pvizeli@syshack.ch
License: BSD License
Download-URL: https://github.com/pvizeli/yahooweather/tarball/0.10
Keywords: weather,yahoo,interface,wrapper,api
Platform: any
Classifier: Programming Language :: Python
Classifier: Topic :: Software Development :: Libraries :: Python Modules
Classifier: Topic :: Scientific/Engineering :: Atmospheric Science
Classifier: License :: OSI Approved :: BSD License
Classifier: Operating System :: OS Independent
Classifier: Development Status :: 5 - Production/Stable
Classifier: Intended Audience :: Developers
Classifier: Programming Language :: Python :: 3.4
Classifier: Programming Language :: Python :: 3.5
